LICENSE
MANIFEST.in
NOTICE
README.md
pyproject.toml
setup.cfg
setup.py
src/alexe_aws_cdk.aws_elasticloadbalancingv2_targets.egg-info/PKG-INFO
src/alexe_aws_cdk.aws_elasticloadbalancingv2_targets.egg-info/SOURCES.txt
src/alexe_aws_cdk.aws_elasticloadbalancingv2_targets.egg-info/dependency_links.txt
src/alexe_aws_cdk.aws_elasticloadbalancingv2_targets.egg-info/requires.txt
src/alexe_aws_cdk.aws_elasticloadbalancingv2_targets.egg-info/top_level.txt
src/aws_cdk/aws_elasticloadbalancingv2_targets/__init__.py
src/aws_cdk/aws_elasticloadbalancingv2_targets/py.typed
src/aws_cdk/aws_elasticloadbalancingv2_targets/_jsii/__init__.py
src/aws_cdk/aws_elasticloadbalancingv2_targets/_jsii/aws-elasticloadbalancingv2-targets@1.166.1.jsii.tgz