Metadata-Version: 2.1
Name: alexe-aws-cdk.aws-elasticloadbalancingv2-targets
Version: 1.166.1
Summary: Integration targets for AWS ElasticLoadBalancingV2
Home-page: https://github.com/aws/aws-cdk
Author: Amazon Web Services
License: Apache-2.0
Project-URL: Source, https://github.com/aws/aws-cdk.git
Platform: UNKNOWN
Classifier: Intended Audience :: Developers
Classifier: Operating System :: OS Independent
Classifier: Programming Language :: JavaScript
Classifier: Programming Language :: Python :: 3 :: Only
Classifier: Programming Language :: Python :: 3.7
Classifier: Programming Language :: Python :: 3.8
Classifier: Programming Language :: Python :: 3.9
Classifier: Programming Language :: Python :: 3.10
Classifier: Typing :: Typed
Classifier: Development Status :: 5 - Production/Stable
Classifier: License :: OSI Approved
Classifier: Framework :: AWS CDK
Classifier: Framework :: AWS CDK :: 1
Requires-Python: ~=3.7
License-File: LICENSE
License-File: NOTICE
